Metadata-Version: 2.1
Name: sqla-softdelete
Version: 1.2
Summary: SQLAlchemy soft delete
Home-page: https://github.com/vitaly-efremov/sqla-softdelete
Author: Vitaly Efremov
Author-email: efremov.vitaly@gmail.com
License: GPLv3+
Download-URL: https://github.com/vitaly-efremov/sqla-softdelete/archive/v1.1.tar.gz
Keywords: SQLAlchemy,Soft delete
Platform: UNKNOWN
Classifier: Development Status :: 5 - Production/Stable
Classifier: Intended Audience :: Developers
Classifier: Topic :: Software Development :: Build Tools
Classifier: License :: OSI Approved :: GNU General Public License v3 or later (GPLv3+)
Classifier: Programming Language :: Python :: 3
Classifier: Programming Language :: Python :: 3.4
Classifier: Programming Language :: Python :: 3.5
Classifier: Programming Language :: Python :: 3.6
Classifier: Programming Language :: Python :: 3.7
Classifier: Programming Language :: Python :: 3.8
